mkpkg/__init__.py
mkpkg/__main__.py
mkpkg/_cli.py
mkpkg/template/.pre-commit-config.yaml
mkpkg/template/.readthedocs.yml
mkpkg/template/COPYING.j2
mkpkg/template/README.rst.j2
mkpkg/template/codecov.yml
mkpkg/template/noxfile.py.j2
mkpkg/template/pyproject.toml.j2
mkpkg/template/tests.py.j2
mkpkg/template/.github/FUNDING.yml
mkpkg/template/.github/SECURITY.md.j2
mkpkg/template/.github/dependabot.yml
mkpkg/template/.github/release.yml
mkpkg/template/.github/workflows/ci.yml.j2
mkpkg/template/docs/conf.py.j2
mkpkg/template/docs/index.rst
mkpkg/template/docs/requirements.in.j2
mkpkg/template/package/__init__.py.j2
mkpkg/template/package/__main__.py.j2
mkpkg/template/package/_build.py.j2
mkpkg/template/package/_cli.py.j2
mkpkg/template/package/tests/test_integration.py.j2
mkpkg/tests/__init__.py
mkpkg/tests/test_integration.py
mkpkg-2025.11.5.dist-info/METADATA
mkpkg-2025.11.5.dist-info/WHEEL
mkpkg-2025.11.5.dist-info/entry_points.txt
mkpkg-2025.11.5.dist-info/licenses/COPYING
mkpkg-2025.11.5.dist-info/RECORD
