Metadata-Version: 2.4
Name: mkpkg
Version: 2025.11.5
Summary: A package @Julian uses to create Python packages.
Project-URL: Documentation, https://mkpkg.readthedocs.io/
Project-URL: Homepage, https://github.com/Julian/mkpkg
Project-URL: Issues, https://github.com/Julian/mkpkg/issues/
Project-URL: Funding, https://github.com/sponsors/Julian
Project-URL: Source, https://github.com/Julian/mkpkg
Author-email: Julian Berman <Julian+mkpkg@GrayVines.com>
License-Expression: MIT
License-File: COPYING
Keywords: packaging,templating
Classifier: Development Status :: 5 - Production/Stable
Classifier: Intended Audience :: Developers
Classifier: Operating System :: OS Independent
Classifier: Programming Language :: Python
Classifier: Programming Language :: Python :: 3
Classifier: Programming Language :: Python :: 3.13
Classifier: Programming Language :: Python :: 3.14
Classifier: Programming Language :: Python :: Implementation :: CPython
Classifier: Programming Language :: Python :: Implementation :: PyPy
Requires-Python: >=3.13
Requires-Dist: click
Requires-Dist: jinja2
Requires-Dist: sphinx
